.gitignore
LICENSE
README.md
pyproject.toml
.github/actions/setup/action.yml
.github/actions/test/action.yml
.github/workflows/lint.yml
.github/workflows/publish.yml
.github/workflows/test.yml
pystrukts/__init__.py
pystrukts/_version.py
pystrukts/max_heap.py
pystrukts/union_find.py
pystrukts.egg-info/PKG-INFO
pystrukts.egg-info/SOURCES.txt
pystrukts.egg-info/dependency_links.txt
pystrukts.egg-info/requires.txt
pystrukts.egg-info/top_level.txt
pystrukts/graph/__init__.py
pystrukts/graph/adjacency_list.py
pystrukts/graph/adjacency_matrix.py
pystrukts/graph/graph.py
pystrukts/list/__init__.py
pystrukts/list/doubly_linked_list.py
pystrukts/list/linked_list.py
pystrukts/list/singly_linked_list.py
pystrukts/tree/__init__.py
pystrukts/tree/binary_search_tree.py
pystrukts/tree/binary_tree.py
pystrukts/tree/fenwick_tree.py
pystrukts/tree/generic_tree.py
pystrukts/tree/trie.py
tests/__init__.py
tests/test_adjacency_list.py
tests/test_adjacency_matrix.py
tests/test_binary_search_tree.py
tests/test_binary_tree.py
tests/test_doubly_linked_list.py
tests/test_fenwick_tree.py
tests/test_generic_tree.py
tests/test_max_heap.py
tests/test_singly_linked_list.py
tests/test_trie.py
tests/test_union_find.py