Metadata-Version: 2.1
Name: pystrukts
Version: 1.0.0
Summary: Advanced data structures for Python.
Author-email: Rubén Pérez Mercado <rubenpermerc@gmail.com>
License:                                  Apache License
Project-URL: Repository, https://github.com/rubenperezm/pystrukts
Project-URL: Issues, https://github.com/rubenperezm/pystrukts/issues
Project-URL: Changelog, https://github.com/rubenperezm/pystrukts/blob/main/CHANGELOG.md
Keywords: data structures,structures,tree,graph,list,heap,trie,union find,pystrukts
Classifier: License :: OSI Approved :: Apache Software License
Classifier: Programming Language :: Python
Classifier: Programming Language :: Python :: 3
Classifier: Programming Language :: Python :: 3.8
Classifier: Programming Language :: Python :: 3.9
Classifier: Programming Language :: Python :: 3.10
Classifier: Programming Language :: Python :: 3.11
Classifier: Programming Language :: Python :: 3.12
Requires-Python: >=3.8
License-File: LICENSE
Provides-Extra: dev
Requires-Dist: pytest>=6.0; extra == "dev"
Requires-Dist: pylint; extra == "dev"
